expross/__init__.py
expross/context.py
expross/cors.py
expross/error.py
expross/errors.py
expross/log.py
expross/main.py
expross/middleware.py
expross/resource.py
expross/response.py
expross/routes.py
expross/types.py
expross/utils.py
Expross-1.1.1.dist-info/LICENSE.md
Expross-1.1.1.dist-info/METADATA
Expross-1.1.1.dist-info/WHEEL
Expross-1.1.1.dist-info/top_level.txt
Expross-1.1.1.dist-info/RECORD
