Metadata-Version: 2.1
Name: Expross
Version: 1.1.1
Summary: Expross is a lightweight web server to introduce JavaScript developers familiar with Express to Python.
Home-page: https://github.com/mauro-balades/expross
Author: Mauro Balades
Author-email: mauro.balades@tutanota.com
License: MIT
Project-URL: Documentation, https://mauro-balades.gitbook.io/expross/
Platform: UNKNOWN
Classifier: Development Status :: 5 - Production/Stable
Classifier: Environment :: MacOS X
Classifier: Environment :: Win32 (MS Windows)
Classifier: Environment :: X11 Applications
Classifier: Intended Audience :: Developers
Classifier: License :: OSI Approved :: BSD License
Classifier: Operating System :: MacOS :: MacOS X
Classifier: Operating System :: Microsoft :: Windows
Classifier: Operating System :: POSIX :: Linux
Classifier: Programming Language :: Python :: 3
Classifier: Programming Language :: Python :: 3.6
Classifier: Programming Language :: Python :: 3.7
Classifier: Programming Language :: Python :: 3.8
Classifier: Programming Language :: Python :: 3.9
Classifier: Topic :: Software Development :: Libraries :: Python Modules
License-File: LICENSE.md
